LICENSE
MANIFEST.in
README.md
setup.py
bin/opencanary.tac
bin/opencanaryd
build_scripts/generate_macOS_launchctl_service_files.py
opencanary/__init__.py
opencanary/config.py
opencanary/honeycred.py
opencanary/iphelper.py
opencanary/logger.py
opencanary/data/settings-usermodule.json
opencanary/data/settings.json
opencanary/modules/__init__.py
opencanary/modules/des.py
opencanary/modules/example0.py
opencanary/modules/example1.py
opencanary/modules/ftp.py
opencanary/modules/git.py
opencanary/modules/http.py
opencanary/modules/httpproxy.py
opencanary/modules/https.py
opencanary/modules/mssql.py
opencanary/modules/mysql.py
opencanary/modules/ntp.py
opencanary/modules/portscan.py
opencanary/modules/rdp.py
opencanary/modules/redis.py
opencanary/modules/samba.py
opencanary/modules/sip.py
opencanary/modules/snmp.py
opencanary/modules/ssh.py
opencanary/modules/tcpbanner.py
opencanary/modules/telnet.py
opencanary/modules/testpdf.py
opencanary/modules/tftp.py
opencanary/modules/vnc.py
opencanary/modules/data/http/skin/basicLogin/403.html
opencanary/modules/data/http/skin/basicLogin/404.html
opencanary/modules/data/http/skin/basicLogin/index.html
opencanary/modules/data/http/skin/nasLogin/403.html
opencanary/modules/data/http/skin/nasLogin/404.html
opencanary/modules/data/http/skin/nasLogin/index.html
opencanary/modules/data/http/skin/nasLogin/static/css/desktop.css
opencanary/modules/data/http/skin/nasLogin/static/css/ext-all.css
opencanary/modules/data/http/skin/nasLogin/static/css/style.css
opencanary/modules/data/http/skin/nasLogin/static/css/ux-all.css
opencanary/modules/data/http/skin/nasLogin/static/css/xtheme-gray.css
opencanary/modules/data/http/skin/nasLogin/static/fonts/roboto.woff
opencanary/modules/data/http/skin/nasLogin/static/img/02.jpg
opencanary/modules/data/http/skin/nasLogin/static/img/favicon.ico
opencanary/modules/data/http/skin/nasLogin/static/img/icon_dsm_16.png
opencanary/modules/data/http/skin/nasLogin/static/img/icon_dsm_32.png
opencanary_fork.egg-info/PKG-INFO
opencanary_fork.egg-info/SOURCES.txt
opencanary_fork.egg-info/dependency_links.txt
opencanary_fork.egg-info/requires.txt
opencanary_fork.egg-info/top_level.txt